setup.py
henry_utils/__init__.py
henry_utils/sqlserver/__init__.py
henry_utils/sqlserver/config.py
henry_utils/sqlserver/server.py
henry_utils_test.egg-info/PKG-INFO
henry_utils_test.egg-info/SOURCES.txt
henry_utils_test.egg-info/dependency_links.txt
henry_utils_test.egg-info/top_level.txt