Metadata-Version: 1.2
Name: henry-utils-test
Version: 1.0.3
Summary: to automatic create spark sql file 
Home-page: UNKNOWN
Author: Henry Liu
Author-email: 2224546920@qq.com
Maintainer: Henry Liu
License: UNKNOWN
Platform: UNKNOWN
Classifier: Development Status :: 4 - Beta
Classifier: License :: OSI Approved :: Apache Software License
Classifier: Operating System :: OS Independent
Classifier: Programming Language :: Python :: 3
Classifier: Programming Language :: Python :: 3.5
Classifier: Programming Language :: Python :: 3.6
Classifier: Programming Language :: Python :: 3.7
Classifier: Programming Language :: Python :: 3.8
Classifier: Programming Language :: Python :: 3.9
Classifier: Topic :: Utilities
Requires: pymssql
